tariochbctools/__init__.py
tariochbctools/importers/__init__.py
tariochbctools/importers/awardwalletimp/__init__.py
tariochbctools/importers/awardwalletimp/config.py
tariochbctools/importers/awardwalletimp/importer.py
tariochbctools/importers/bcge/__init__.py
tariochbctools/importers/bcge/importer.py
tariochbctools/importers/bitst/__init__.py
tariochbctools/importers/bitst/importer.py
tariochbctools/importers/blockchain/__init__.py
tariochbctools/importers/blockchain/importer.py
tariochbctools/importers/cembrastatement/__init__.py
tariochbctools/importers/cembrastatement/importer.py
tariochbctools/importers/general/__init__.py
tariochbctools/importers/general/deduplication.py
tariochbctools/importers/general/mailAdapterImporter.py
tariochbctools/importers/general/mt940importer.py
tariochbctools/importers/general/priceLookup.py
tariochbctools/importers/ibkr/__init__.py
tariochbctools/importers/ibkr/importer.py
tariochbctools/importers/neon/__init__.py
tariochbctools/importers/neon/importer.py
tariochbctools/importers/netbenefits/__init__.py
tariochbctools/importers/netbenefits/importer.py
tariochbctools/importers/nordigen/__init__.py
tariochbctools/importers/nordigen/importer.py
tariochbctools/importers/nordigen/nordigen_config.py
tariochbctools/importers/postfinance/__init__.py
tariochbctools/importers/postfinance/importer.py
tariochbctools/importers/quickfile/__init__.py
tariochbctools/importers/quickfile/importer.py
tariochbctools/importers/radicant/__init__.py
tariochbctools/importers/radicant/importer.py
tariochbctools/importers/raiffeisench/importer.py
tariochbctools/importers/revolut/__init__.py
tariochbctools/importers/revolut/importer.py
tariochbctools/importers/schedule/__init__.py
tariochbctools/importers/schedule/importer.py
tariochbctools/importers/swisscard/__init__.py
tariochbctools/importers/swisscard/importer.py
tariochbctools/importers/transferwise/__init__.py
tariochbctools/importers/transferwise/importer.py
tariochbctools-1.6.0.dist-info/licenses/LICENSE.txt
tariochbctools-1.6.0.dist-info/METADATA
tariochbctools-1.6.0.dist-info/WHEEL
tariochbctools-1.6.0.dist-info/entry_points.txt
tariochbctools-1.6.0.dist-info/top_level.txt
tariochbctools-1.6.0.dist-info/RECORD
