Metadata-Version: 2.4
Name: tariochbctools
Version: 1.6.0
Summary: Importers, plugins and price fetchers for Beancount
Home-page: https://github.com/tarioch/beancounttools/
Author: Patrick Ruckstuhl
Author-email: patrick@ch.tario.org
License: MIT
Project-URL: Bug Tracker, https://github.com/tarioch/beancounttools/issues
Project-URL: Documentation, https://tariochbctools.rtfd.io
Project-URL: Source Code, https://github.com/tarioch/beancounttools/
Platform: any
Classifier: Development Status :: 3 - Alpha
Classifier: Programming Language :: Python
Classifier: Intended Audience :: Developers
Classifier: Topic :: Office/Business :: Financial
Classifier: Topic :: Office/Business :: Financial :: Accounting
Classifier: Topic :: Office/Business :: Financial :: Investment
License-File: LICENSE.txt
Requires-Dist: importlib-metadata; python_version < "3.8"
Requires-Dist: awardwallet>=0.2
Requires-Dist: beancount>=3
Requires-Dist: beangulp
Requires-Dist: beanprice
Requires-Dist: bitstampclient
Requires-Dist: mt-940
Requires-Dist: pyyaml
Requires-Dist: ibflex
Requires-Dist: requests
Requires-Dist: camelot-py
Requires-Dist: opencv-python-headless
Requires-Dist: blockcypher
Requires-Dist: imap-tools
Requires-Dist: undictify
Requires-Dist: rsa
Provides-Extra: testing
Requires-Dist: pytest; extra == "testing"
Requires-Dist: pytest-cov; extra == "testing"
Requires-Dist: pytest-mock; extra == "testing"
Requires-Dist: flake8; extra == "testing"
Requires-Dist: black; extra == "testing"
Requires-Dist: isort; extra == "testing"
Dynamic: license-file
